sluarch/__init__.py
sluarch/sluarch.py
sluarch-2024.5.16.dist-info/LICENSE
sluarch-2024.5.16.dist-info/METADATA
sluarch-2024.5.16.dist-info/WHEEL
sluarch-2024.5.16.dist-info/RECORD
