Metadata-Version: 2.1
Name: sluarch
Version: 2024.5.16
Summary: SlµArch (Sleep MicroArchitecture: open-source Python package to analyse sleep microarchitecture.
License: Apache-2.0
Author: Simon J. Guillot
Requires-Python: >=3.10,<4.0
Classifier: License :: OSI Approved :: Apache Software License
Classifier: Programming Language :: Python :: 3
Classifier: Programming Language :: Python :: 3.10
Classifier: Programming Language :: Python :: 3.11
Classifier: Programming Language :: Python :: 3.12
